MANIFEST.in
README
setup.cfg
setup.py
Pylares.egg-info/PKG-INFO
Pylares.egg-info/SOURCES.txt
Pylares.egg-info/dependency_links.txt
Pylares.egg-info/top_level.txt
pylares/__init__.py
pylares/listas.py
pylares/logica.py
pylares/numeros.py
pylares/terminal.py
pylares/texto.py
pylares/utilidades.py
pylares/contrib/__init__.py
pylares/contrib/getch.py
pylares/contrib/terminal_w.py
pylares/interfaz_grafica/__init__.py
pylares/interfaz_grafica/tkinter/Boton.py
pylares/interfaz_grafica/tkinter/BotonesDeOpcion.py
pylares/interfaz_grafica/tkinter/CasillasDeVerificacion.py
pylares/interfaz_grafica/tkinter/Contenedores.py
pylares/interfaz_grafica/tkinter/ControlGenerico.py
pylares/interfaz_grafica/tkinter/Entrada.py
pylares/interfaz_grafica/tkinter/EntradaMultilinea.py
pylares/interfaz_grafica/tkinter/Etiqueta.py
pylares/interfaz_grafica/tkinter/Imagen.py
pylares/interfaz_grafica/tkinter/ListaDesplegable.py
pylares/interfaz_grafica/tkinter/ListaDesplegada.py
pylares/interfaz_grafica/tkinter/Temporizador.py
pylares/interfaz_grafica/tkinter/Ventana.py
pylares/interfaz_grafica/tkinter/__init__.py
pylares/test/__init__.py
pylares/test/test_listas.py
pylares/test/test_logica.py
pylares/test/test_numeros.py
pylares/test/test_terminal.py
pylares/test/test_texto.py