Metadata-Version: 1.1
Name: Pylares
Version: 0.0.1
Summary: Helper to use and teach python in Latin American schools.
Home-page: https://pypi.python.org/pypi/Pylares
Author: Mariano D'Agostino
Author-email: dagostinom [at] gmail
License: UNKNOWN
Download-URL: https://github.com/pylares/pylares
Platform: UNKNOWN
Classifier: Development Status :: 3 - Alpha
Classifier: Intended Audience :: Education
Classifier: License :: OSI Approved :: Apache Software License
Classifier: Natural Language :: Spanish
